KCExpr/KCExpr.py
KCExpr/__init__.py
KCExpr-1.0.0.dist-info/LICENSE
KCExpr-1.0.0.dist-info/METADATA
KCExpr-1.0.0.dist-info/WHEEL
KCExpr-1.0.0.dist-info/top_level.txt
KCExpr-1.0.0.dist-info/RECORD
