Metadata-Version: 2.1
Name: KCExpr
Version: 1.0.0
Summary: A small mathematics package including an expression parser
Home-page: https://github.com/Catterall/KCExpr
Author: Kyle James Catterall
Author-email: kylejamescatterall16@gmai.com
License: UNKNOWN
Project-URL: Bug Tracker, https://github.com/Catterall/KCExpr/issues
Platform: UNKNOWN
Classifier: Programming Language :: Python :: 3
Classifier: License :: OSI Approved :: MIT License
Classifier: Operating System :: OS Independent
Requires-Python: >=3.6
License-File: LICENSE
Requires-Dist: regex
